{
  "<OOV>": 1,
  "payment": 2,
  "store": 3,
  "credit": 4,
  "card": 5,
  "grocery": 6,
  "company": 7,
  "biweekly": 8,
  "paycheck": 9,
  "withdrawal": 10,
  "amazon": 11,
  "rent": 12,
  "restaurant": 13,
  "mortgage": 14,
  "salary": 15,
  "deposit": 16,
  "hardware": 17,
  "atm": 18,
  "spotify": 19,
  "unknown": 20,
  "merchant": 21,
  "gas": 22,
  "water": 23,
  "transfer": 24,
  "refund": 25,
  "starbucks": 26,
  "netflix": 27,
  "apartment": 28,
  "client": 29,
  "fiverr": 30,
  "pending": 31,
  "transaction": 32,
  "payroll": 33,
  "bp": 34,
  "hoa": 35,
  "fees": 36,
  "property": 37,
  "management": 38,
  "landlord": 39,
  "consulting": 40,
  "fee": 41,
  "miscellaneous": 42,
  "internet": 43,
  "provider": 44,
  "barbershop": 45,
  "freelance": 46,
  "contract": 47,
  "work": 48,
  "cash": 49,
  "city": 50,
  "state": 51,
  "farm": 52,
  "side": 53,
  "gig": 54,
  "income": 55,
  "upwork": 56,
  "power": 57,
  "monthly": 58,
  "american": 59,
  "tavern": 60,
  "shell": 61,
  "employer": 62,
  "brewing": 63,
  "direct": 64,
  "phone": 65,
  "charges": 66,
  "service": 67,
  "physical": 68,
  "therapy": 69,
  "dermatologist": 70,
  "hospital": 71,
  "airlines": 72,
  "concert": 73,
  "venue": 74,
  "apple": 75,
  "hair": 76,
  "salon": 77,
  "urgent": 78,
  "care": 79,
  "walgreens": 80,
  "youtube": 81,
  "premium": 82,
  "amc": 83,
  "theatres": 84,
  "gym": 85,
  "membership": 86,
  "dentist": 87,
  "office": 88,
  "hulu": 89,
  "eye": 90,
  "doctor": 91,
  "enterprise": 92,
  "rental": 93,
  "att": 94,
  "wireless": 95,
  "spectrum": 96,
  "xbox": 97,
  "brunch": 98,
  "target": 99,
  "united": 100,
  "hertz": 101,
  "lab": 102,
  "corp": 103,
  "ach": 104,
  "thai": 105,
  "aldi": 106,
  "kroger": 107,
  "toll": 108,
  "road": 109,
  "jiffy": 110,
  "lube": 111,
  "t": 112,
  "mobile": 113,
  "cvs": 114,
  "pharmacy": 115,
  "ross": 116,
  "venmo": 117,
  "pizza": 118,
  "best": 119,
  "buy": 120,
  "shop": 121,
  "fuel": 122,
  "amtrak": 123,
  "insurance": 124,
  "hbo": 125,
  "max": 126,
  "steam": 127,
  "games": 128,
  "playstation": 129,
  "nike": 130,
  "bank": 131,
  "zelle": 132,
  "place": 133,
  "food": 134,
  "department": 135,
  "comcast": 136,
  "regal": 137,
  "cinemas": 138,
  "music": 139,
  "wire": 140,
  "fancy": 141,
  "greek": 142,
  "heb": 143,
  "wegmans": 144,
  "lion": 145,
  "trader": 146,
  "joes": 147,
  "sprouts": 148,
  "parking": 149,
  "meter": 150,
  "delta": 151,
  "uber": 152,
  "disney": 153,
  "plus": 154,
  "nordstrom": 155,
  "paypal": 156,
  "chevron": 157,
  "chick": 158,
  "fil": 159,
  "a": 160,
  "walmart": 161,
  "safeway": 162,
  "publix": 163,
  "auto": 164,
  "repair": 165,
  "lyft": 166,
  "cox": 167,
  "bowling": 168,
  "alley": 169,
  "lowes": 170,
  "ikea": 171,
  "home": 172,
  "depot": 173,
  "ebay": 174,
  "quiktrip": 175,
  "movie": 176,
  "theater": 177,
  "italian": 178,
  "meijer": 179,
  "lidl": 180,
  "whole": 181,
  "foods": 182,
  "exxonmobil": 183,
  "verizon": 184,
  "macys": 185,
  "bed": 186,
  "bath": 187,
  "beyond": 188,
  "mexican": 189,
  "s": 190,
  "diner": 191,
  "burger": 192,
  "king": 193,
  "audible": 194,
  "tj": 195,
  "maxx": 196,
  "sushi": 197,
  "costco": 198,
  "papa": 199,
  "johns": 200,
  "coffee": 201,
  "chipotle": 202,
  "bistro": 203,
  "dunkin": 204,
  "subway": 205,
  "etsy": 206,
  "wayfair": 207,
  "bojangles": 208,
  "bbq": 209,
  "video": 210,
  "deli": 211,
  "irish": 212,
  "mike": 213,
  "construction": 214,
  "co": 215,
  "valero": 216,
  "seafood": 217,
  "roadside": 218,
  "olive": 219,
  "garden": 220,
  "bar": 221,
  "panera": 222,
  "bread": 223,
  "taco": 224,
  "bell": 225,
  "wendys": 226,
  "hut": 227,
  "ihop": 228,
  "electric": 229,
  "japanese": 230,
  "station": 231,
  "mediterranean": 232,
  "steakhouse": 233,
  "belgian": 234,
  "chili": 235,
  "tiny": 236,
  "pub": 237,
  "blue": 238,
  "sky": 239,
  "market": 240,
  "liquor": 241,
  "go": 242,
  "mart": 243,
  "circle": 244,
  "k": 245,
  "wendy": 246,
  "conoco": 247,
  "exxon": 248,
  "german": 249,
  "truck": 250,
  "latin": 251,
  "new": 252,
  "york": 253,
  "bakery": 254,
  "vietnamese": 255,
  "hawaiian": 256,
  "grill": 257,
  "sheetz": 258,
  "buffalo": 259,
  "wild": 260,
  "wings": 261,
  "mcdonalds": 262,
  "dominos": 263,
  "applebees": 264,
  "online": 265
}